dsocli/__init__.py
dsocli/__main__.py
dsocli/artifacts.py
dsocli/aws_s3_utils.py
dsocli/aws_ssm_utils.py
dsocli/cli.py
dsocli/cli_constants.py
dsocli/cli_utils.py
dsocli/click_extend.py
dsocli/configs.py
dsocli/constants.py
dsocli/contexts.py
dsocli/dict_utils.py
dsocli/editor.py
dsocli/enum_utils.py
dsocli/exceptions.py
dsocli/file_utils.py
dsocli/local_utils.py
dsocli/logger.py
dsocli/network_utils.py
dsocli/networks.py
dsocli/package.json
dsocli/packages.py
dsocli/pager.py
dsocli/parameters.py
dsocli/providers.py
dsocli/releases.py
dsocli/remote_configs.py
dsocli/secrets.py
dsocli/settings.py
dsocli/shell_utils.py
dsocli/stages.py
dsocli/templates.py
dsocli/version.py
dsocli/provider/__init__.py
dsocli/provider/artifactory/__init__.py
dsocli/provider/artifactory/aws/__init__.py
dsocli/provider/artifactory/aws/s3/__init__.py
dsocli/provider/artifactory/aws/s3/v1/__init__.py
dsocli/provider/artifactory/aws/s3/v1/main.py
dsocli/provider/artifactory/local/__init__.py
dsocli/provider/artifactory/local/v1/__init__.py
dsocli/provider/artifactory/local/v1/main.py
dsocli/provider/config/__init__.py
dsocli/provider/config/aws/__init__.py
dsocli/provider/config/aws/ssm/__init__.py
dsocli/provider/config/aws/ssm/v1/__init__.py
dsocli/provider/config/aws/ssm/v1/main.py
dsocli/provider/config/local/__init__.py
dsocli/provider/config/local/v1/__init__.py
dsocli/provider/config/local/v1/main.py
dsocli/provider/package/__init__.py
dsocli/provider/package/aws/__init__.py
dsocli/provider/package/aws/cfn/__init__.py
dsocli/provider/package/aws/cfn/v1/__init__.py
dsocli/provider/package/aws/cfn/v1/main.py
dsocli/provider/package/docker/__init__.py
dsocli/provider/package/docker/v1/__init__.py
dsocli/provider/package/docker/v1/main.py
dsocli/provider/parameter/__init__.py
dsocli/provider/parameter/aws/__init__.py
dsocli/provider/parameter/aws/ssm/__init__.py
dsocli/provider/parameter/aws/ssm/v1/__init__.py
dsocli/provider/parameter/aws/ssm/v1/main.py
dsocli-1.0.197.dist-info/LICENSE.md
dsocli-1.0.197.dist-info/METADATA
dsocli-1.0.197.dist-info/WHEEL
dsocli-1.0.197.dist-info/entry_points.txt
dsocli-1.0.197.dist-info/top_level.txt
dsocli-1.0.197.dist-info/RECORD
